turtl_backup/__init__.py
turtl_backup/gui.py
turtl_backup/tcrypt.py
turtl_backup/turtl.py
turtl_backup/turtl_backup.py
turtl_backup-0.1.1.dist-info/METADATA
turtl_backup-0.1.1.dist-info/WHEEL
turtl_backup-0.1.1.dist-info/entry_points.txt
turtl_backup-0.1.1.dist-info/top_level.txt
turtl_backup-0.1.1.dist-info/RECORD
