Metadata-Version: 2.1
Name: turtl-backup
Version: 0.1.1
Summary: Tool to backup a turtl account.
Home-page: https://github.com/JulienPalard/turtle-backup
Author: Julien Palard
Author-email: julien@palard.fr
License: MIT
Keywords: turtl backup
Platform: UNKNOWN
Classifier: Development Status :: 2 - Pre-Alpha
Classifier: Intended Audience :: Developers
Classifier: License :: OSI Approved :: MIT License
Classifier: Natural Language :: English
Classifier: Programming Language :: Python :: 3
Classifier: Programming Language :: Python :: 3.3
Classifier: Programming Language :: Python :: 3.4
Classifier: Programming Language :: Python :: 3.5
Classifier: Programming Language :: Python :: 3.6
Requires-Dist: requests
Requires-Dist: cryptography
